{"assets":{"31A3698BF8FBB7BC5AE627ABDB1D881D":{"type":"texture","index":1,"url":{"native":"assets\/99E686DA-1695-4F00-B0BF-20ACF24980F0.pdf"},"width":1920,"height":1080},"E449B772D8493F6830EB39EAAC7AA5E3":{"type":"texture","index":0,"url":{"native":"assets\/99E686DA-1695-4F00-B0BF-20ACF24980F0.pdf"},"width":1920,"height":1080}},"events":[{"effects":[{"beginTime":0,"baseLayer":{"animations":[],"initialState":{"affineTransform":[1,0,0,1,0,0],"masksToBounds":false,"rotation":0,"scale":1,"position":{"pointX":960,"pointY":540},"width":1920,"sublayerTransform":[1,0,0,0,0,1,0,0,0,0,1,0,0,0,0,1],"contentsRect":{"y":0,"x":0,"width":1,"height":1},"opacity":1,"edgeAntialiasingMask":251658240,"height":1080,"hidden":false,"anchorPoint":{"pointX":0.5,"pointY":0.5}},"objectID":"0","layers":[{"animations":[],"initialState":{"affineTransform":[1,0,0,1,0,0],"masksToBounds":false,"rotation":0,"scale":1,"position":{"pointX":960,"pointY":540},"width":1920,"sublayerTransform":[1,0,0,0,0,1,0,0,0,0,1,-0.00035007912466775983,0,0,0,1],"contentsRect":{"y":0,"x":0,"width":1,"height":1},"opacity":1,"edgeAntialiasingMask":251658240,"height":1080,"hidden":false,"anchorPoint":{"pointX":0.5,"pointY":0.5}},"layers":[{"animations":[],"layers":[],"texturedRectangle":{"isBackgroundTexture":false,"singleTextureOpacity":1,"textureType":0,"textBaseline":0,"textXHeight":0,"isVerticalText":false},"initialState":{"affineTransform":[1,0,0,1,0,0],"masksToBounds":false,"rotation":0,"scale":1,"position":{"pointX":960,"pointY":540},"width":1920,"sublayerTransform":[1,0,0,0,0,1,0,0,0,0,1,0,0,0,0,1],"contentsRect":{"y":0,"x":0,"width":1,"height":1},"opacity":1,"edgeAntialiasingMask":0,"height":1080,"hidden":false,"anchorPoint":{"pointX":0.5,"pointY":0.5}},"texture":"31A3698BF8FBB7BC5AE627ABDB1D881D"},{"animations":[{"additive":false,"timeOffset":0,"beginTime":0,"from":{"scalar":false},"repeatCount":0,"fillMode":"both","duration":0.001,"autoreverses":false,"property":"hidden","to":{"scalar":true},"removedOnCompletion":false}],"layers":[],"texturedRectangle":{"isBackgroundTexture":false,"singleTextureOpacity":1,"textureType":0,"textBaseline":0,"textXHeight":0,"isVerticalText":false},"initialState":{"affineTransform":[1,0,0,1,0,0],"masksToBounds":false,"rotation":0,"scale":1,"position":{"pointX":960,"pointY":540},"width":1920,"sublayerTransform":[1,0,0,0,0,1,0,0,0,0,1,0,0,0,0,1],"contentsRect":{"y":0,"x":0,"width":1,"height":1},"opacity":1,"edgeAntialiasingMask":0,"height":1080,"hidden":false,"anchorPoint":{"pointX":0.5,"pointY":0.5}},"texture":"E449B772D8493F6830EB39EAAC7AA5E3"}]}]},"effects":[],"duration":0.001,"type":"transition","attributes":{"direction":0},"name":"none","objectID":"0"}],"automaticPlay":false,"hyperlinks":[],"accessibility":[{"text":"Examples","targetRectangle":{"y":40.500000238418579,"x":598.34846353530884,"width":101.56430443857971,"height":30}},{"text":"AI","targetRectangle":{"y":40.500000238418579,"x":1206.7058125734329,"width":21.019038958274905,"height":30}},{"text":"Human to AI","targetRectangle":{"y":40.500000238418579,"x":1400.0002508163452,"width":129.16380964397831,"height":30}},{"text":"Analytics ","targetRectangle":{"y":40.500000238418579,"x":755.09898904576767,"width":100.90691261457323,"height":38}},{"text":"Business analytics applies data analysis, statistical models & quantitative techniques to solve complex business challenges and support data-driven decision-making","targetRectangle":{"y":367.44354629516602,"x":231.366943359375,"width":1392.6506772637367,"height":162}},{"text":"Key Components:","targetRectangle":{"y":588.44354629516602,"x":231.366943359375,"width":366.2841796875,"height":59}},{"text":"Data Management","targetRectangle":{"y":647.44354629516602,"x":231.366943359375,"width":346.43886387348175,"height":59}},{"text":"Data Mining","targetRectangle":{"y":706.44354629516602,"x":231.366943359375,"width":223.69620367884636,"height":59}},{"text":"Statistical Analysis","targetRectangle":{"y":765.44354629516602,"x":231.366943359375,"width":344.09202888607979,"height":59}},{"text":"Decision-Making Models","targetRectangle":{"y":824.44354629516602,"x":231.366943359375,"width":466.29977747797966,"height":59}},{"text":"Performance Metrics","targetRectangle":{"y":883.44354629516602,"x":231.366943359375,"width":387.70526111125946,"height":59}},{"text":"Types","targetRectangle":{"y":40.500000238418579,"x":905.19619727134705,"width":62.593203196411196,"height":30}},{"text":"􀩬","targetRectangle":{"y":559.1485595703125,"x":1229.974609375,"width":468.2150200009346,"height":417}},{"text":"Intro","targetRectangle":{"y":41.500000238418579,"x":390.83596932888031,"width":46.679686928109732,"height":30}},{"text":"Defining Business Analytics","targetRectangle":{"y":149.95342254638672,"x":528.84538757801056,"width":862.30919009447098,"height":92}},{"text":"Tools","targetRectangle":{"y":40.500000238418579,"x":491.8332998752594,"width":55.006981825226831,"height":30}},{"text":"Trust","targetRectangle":{"y":40.500000238418579,"x":1286.9692915678024,"width":52.328748318723228,"height":30}},{"text":"Applications","targetRectangle":{"y":40.500000238418579,"x":1018.7277541160583,"width":129.6277475395982,"height":30}}],"baseLayer":{"animations":[],"initialState":{"affineTransform":[1,0,0,1,0,0],"masksToBounds":false,"rotation":0,"scale":1,"position":{"pointX":960,"pointY":540},"width":1920,"sublayerTransform":[1,0,0,0,0,1,0,0,0,0,1,0,0,0,0,1],"contentsRect":{"y":0,"x":0,"width":1,"height":1},"opacity":1,"edgeAntialiasingMask":251658240,"height":1080,"hidden":false,"anchorPoint":{"pointX":0.5,"pointY":0.5}},"objectID":"0","layers":[{"animations":[],"initialState":{"affineTransform":[1,0,0,1,0,0],"masksToBounds":false,"rotation":0,"scale":1,"position":{"pointX":960,"pointY":540},"width":1920,"sublayerTransform":[1,0,0,0,0,1,0,0,0,0,1,-0.00035007912466775983,0,0,0,1],"contentsRect":{"y":0,"x":0,"width":1,"height":1},"opacity":1,"edgeAntialiasingMask":251658240,"height":1080,"hidden":false,"anchorPoint":{"pointX":0.5,"pointY":0.5}},"layers":[{"animations":[],"layers":[],"texturedRectangle":{"isBackgroundTexture":false,"singleTextureOpacity":1,"textureType":0,"textBaseline":0,"textXHeight":0,"isVerticalText":false},"initialState":{"affineTransform":[1,0,0,1,0,0],"masksToBounds":false,"rotation":0,"scale":1,"position":{"pointX":960,"pointY":540},"width":1920,"sublayerTransform":[1,0,0,0,0,1,0,0,0,0,1,0,0,0,0,1],"contentsRect":{"y":0,"x":0,"width":1,"height":1},"opacity":1,"edgeAntialiasingMask":0,"height":1080,"hidden":false,"anchorPoint":{"pointX":0.5,"pointY":0.5}},"texture":"E449B772D8493F6830EB39EAAC7AA5E3"}]}]}}]}